akshat_nbdev_test/__init__.py
akshat_nbdev_test/_nbdev.py
akshat_nbdev_test/core.py
akshat_nbdev_test-0.0.6.dist-info/LICENSE
akshat_nbdev_test-0.0.6.dist-info/METADATA
akshat_nbdev_test-0.0.6.dist-info/WHEEL
akshat_nbdev_test-0.0.6.dist-info/entry_points.txt
akshat_nbdev_test-0.0.6.dist-info/top_level.txt
akshat_nbdev_test-0.0.6.dist-info/RECORD
