Metadata-Version: 2.1
Name: akshat-nbdev-test
Version: 0.0.6
Summary: A description of your project
Home-page: https://github.com/fastai/akshat_nbdev_test/tree/master/
Author: Your Name
Author-email: akshat.agrawal@codenation.co.in
License: Apache Software License 2.0
Keywords: helper_library heidelberg ml cn
Platform: UNKNOWN
Classifier: Development Status :: 3 - Alpha
Classifier: Intended Audience :: Developers
Classifier: License :: OSI Approved :: Apache Software License
Classifier: Natural Language :: English
Classifier: Programming Language :: Python :: 3.6
Classifier: Programming Language :: Python :: 3.7
Classifier: Programming Language :: Python :: 3.8
Requires-Python: >=3.6
Requires-Dist: pandas
